tox_runtime_env/__init__.py
tox_runtime_env/plugin.py
tox_runtime_env/version.py
tox_runtime_env-0.1.0.dist-info/LICENSE
tox_runtime_env-0.1.0.dist-info/METADATA
tox_runtime_env-0.1.0.dist-info/WHEEL
tox_runtime_env-0.1.0.dist-info/entry_points.txt
tox_runtime_env-0.1.0.dist-info/top_level.txt
tox_runtime_env-0.1.0.dist-info/zip-safe
tox_runtime_env-0.1.0.dist-info/RECORD
