Metadata-Version: 2.1
Name: tox-runtime-env
Version: 0.1.0
Summary: A tox plugin to determine and set environment variables at runtime.
Home-page: https://github.com/equinor/tox-runtime-env
Author: Equinor ASA
Author-email: msfe@equinor.com
Maintainer: Matthew Ferrera
Maintainer-email: msfe@equinor.com
License: MIT
Project-URL: Source, https://github.com/equinor/tox-runtime-env
Project-URL: Tracker, https://github.com/equinor/tox-runtime-env/issues
Keywords: virtual,environments,isolated,testing
Platform: any
Classifier: Development Status :: 4 - Beta
Classifier: Framework :: tox
Classifier: Intended Audience :: Developers
Classifier: Operating System :: OS Independent
Classifier: Topic :: Software Development :: Testing
Classifier: Topic :: Software Development :: Libraries
Classifier: Topic :: Utilities
Classifier: Programming Language :: Python :: 3
Classifier: Programming Language :: Python :: 3.8
Classifier: Programming Language :: Python :: 3.9
Classifier: Programming Language :: Python :: 3.10
Requires-Python: >=3.8
License-File: LICENSE
Requires-Dist: tox (>=3.12.2)
Provides-Extra: testing
Requires-Dist: pytest (>=7.2.0) ; extra == 'testing'
Requires-Dist: pytest-cov (>=4.0.0) ; extra == 'testing'
Requires-Dist: pytest-mock (>=3.10.0) ; extra == 'testing'
Requires-Dist: pytest-xdist (>=3.0.2) ; extra == 'testing'
